[
  {
    "title": "Fallout Anomaly",
    "description": "Seamlessly merging the Stalker series and Fallout 4 universe. It introduces Stalker-like elements into Fallout 4, such as harsh survival mechanics, dangerous mutants, and a gritty atmosphere, offering players a unique and unparalleled gaming experience.",
    "author": "Fallout Anomaly Team",
    "maintainers": [
      "github/NomadsReach"
    ],
    "game": "fallout4",
    "official": true,
    "tags": [
      "Offical",
      "Quests",
      "Hunting",
      "S.T.A.L.K.E.R.",
      "Survival"
    ],
    "nsfw": false,
    "utility_list": false,
    "image_contains_title": false,
    "DisplayVersionOnlyInInstallerView": false,
    "force_down": false,
    "links": {
      "image": "https://raw.githubusercontent.com/NomadsReach/Fallout-Anomaly/master/images/Banner%20Images/Fo4Anomaly27.png",
      "readme": "https://github.com/NomadsReach/Fallout-Anomaly",
      "download": "https://authored-files.wabbajack.org/Fallout Anomaly Beta.wabbajack_7b1a7596-8d58-4fc9-84c5-43560c612b91",
      "machineURL": "Fallout_Anomaly",
      "discordURL": "https://discord.gg/ECuAthsdwJ"
    },
    "download_metadata": {
      "Hash": "vDXbecZZ4/g=",
      "Size": 191409319,
      "NumberOfArchives": 993,
      "SizeOfArchives": 180956213553,
      "NumberOfInstalledFiles": 43579,
      "SizeOfInstalledFiles": 195750073727
    },
    "version": "0.5.2",
    "dateCreated": "1970-01-01T00:00:00Z",
    "dateUpdated": "2024-12-12T23:00:18.6418511Z",
    "repositoryName": ""
  }
]