[
  {
    "title": "Fallout Anomaly",
    "description": "Fallout Anomaly is a true hardcore experience, bringing you as close to realism as possible with mods like Damn Apocalypse, Better Locational Damage, and much more. Packed with new weapons and armor to face harsher challenges, Anomaly also features new enemy types, quests, settlement items, and a complete assortment of textures to elevate your game to modern standards. If you\u2019re searching for that gritty, harsh survival experience, Anomaly has you covered!",
    "author": "Fallout Anomaly Team",
    "maintainers": [
      "github/NomadsReach"
    ],
    "game": "fallout4",
    "official": true,
    "tags": [
      "Offical",
      "Quests",
      "Hunting",
      "S.T.A.L.K.E.R.",
      "Survival"
    ],
    "nsfw": false,
    "utility_list": false,
    "image_contains_title": false,
    "DisplayVersionOnlyInInstallerView": false,
    "force_down": false,
    "links": {
      "image": "https://staticdelivery.nexusmods.com/mods/1151/images/74075/74075-1737956755-915098088.jpeg",
      "readme": "https://github.com/NomadsReach/Fallout-Anomaly",
      "download": "https://authored-files.wabbajack.org/Fallout Anomaly.wabbajack_bb655fef-bb3f-46e1-814a-12c75d3fbc1d",
      "machineURL": "Fallout_Anomaly",
      "discordURL": "https://discord.gg/ECuAthsdwJ"
    },
    "download_metadata": {
      "Hash": "l0EDfOX40zM=",
      "Size": 144382014,
      "NumberOfArchives": 1087,
      "SizeOfArchives": 178313804758,
      "NumberOfInstalledFiles": 48160,
      "SizeOfInstalledFiles": 193043287444
    },
    "version": "0.5.4",
    "dateCreated": "1970-01-01T00:00:00Z",
    "dateUpdated": "2025-01-27T08:47:35.4742541Z",
    "repositoryName": ""
  }
]